agstack/__init__.py
agstack/decorators.py
agstack/events.py
agstack/exceptions.py
agstack/registry.py
agstack/schema.py
agstack/status.py
agstack/config/__init__.py
agstack/config/logger.py
agstack/config/manager.py
agstack/config/types.py
agstack/fastapi/__init__.py
agstack/fastapi/exception.py
agstack/fastapi/middleware.py
agstack/fastapi/offline.py
agstack/fastapi/sse.py
agstack/infra/db/__init__.py
agstack/infra/es/__init__.py
agstack/infra/kg/__init__.py
agstack/infra/mq/__init__.py
agstack/llm/__init__.py
agstack/llm/client.py
agstack/llm/prompts.py
agstack/llm/token.py
agstack/llm/flow/__init__.py
agstack/llm/flow/agent.py
agstack/llm/flow/context.py
agstack/llm/flow/events.py
agstack/llm/flow/exceptions.py
agstack/llm/flow/factory.py
agstack/llm/flow/flow.py
agstack/llm/flow/loader.py
agstack/llm/flow/records.py
agstack/llm/flow/registry.py
agstack/llm/flow/state.py
agstack/llm/flow/tool.py
agstack/security/__init__.py
agstack/security/casbin.py
agstack/security/crypt.py
agstack-1.0.1.dist-info/licenses/LICENSE
agstack-1.0.1.dist-info/METADATA
agstack-1.0.1.dist-info/WHEEL
agstack-1.0.1.dist-info/top_level.txt
agstack-1.0.1.dist-info/RECORD
