Metadata-Version: 2.4
Name: agstack
Version: 1.0.1
Summary: Production-ready toolkit for building FastAPI and LLM applications
Author-email: XtraVisions <gitadmin@xtravisions.com>, Chen Hao <chenhao@xtravisions.com>
Maintainer-email: XtraVisions <gitadmin@xtravisions.com>, Chen Hao <chenhao@xtravisions.com>
License-Expression: MIT
Keywords: fastapi,llm,agents,ai,infrastructure,framework,casbin,openai,logging,configuration
Classifier: Development Status :: 4 - Beta
Classifier: Intended Audience :: Developers
Classifier: Topic :: Software Development :: Libraries :: Application Frameworks
Classifier: Topic :: Software Development :: Libraries :: Python Modules
Classifier: Topic :: Scientific/Engineering :: Artificial Intelligence
Classifier: Framework :: FastAPI
Classifier: Programming Language :: Python :: 3
Classifier: Programming Language :: Python :: 3.12
Classifier: Programming Language :: Python :: 3 :: Only
Classifier: Operating System :: OS Independent
Classifier: Typing :: Typed
Requires-Python: >=3.12
License-File: LICENSE
Requires-Dist: ag-ui-protocol>=0.1.10
Requires-Dist: aio-pika>=9.5.8
Requires-Dist: asyncpg>=0.30.0
Requires-Dist: elasticsearch[async]>=9.2.1
Requires-Dist: fastapi>=0.121.3
Requires-Dist: jwcrypto>=1.5.6
Requires-Dist: loguru>=0.7.3
Requires-Dist: nebula3-python>=3.8.3
Requires-Dist: openai>=2.16.0
Requires-Dist: passlib[bcrypt]>=1.7.4
Requires-Dist: pycasbin>=2.6.0
Requires-Dist: pydantic>=2.12.4
Requires-Dist: python-multipart>=0.0.20
Requires-Dist: requests>=2.32.5
Requires-Dist: sqlalchemy[asyncio]>=2.0.46
Requires-Dist: sqlobjects>=1.0.16
Requires-Dist: tiktoken>=0.12.0
Requires-Dist: uvicorn>=0.38.0
Dynamic: license-file
